vidjon_messenger_api/__init__.py
vidjon_messenger_api/__main__.py
vidjon_messenger_api/app.py
vidjon_messenger_api/db.py
vidjon_messenger_api/security.py
vidjon_messenger_api/models/__init__.py
vidjon_messenger_api/models/message.py
vidjon_messenger_api/models/user.py
vidjon_messenger_api/resources/__init__.py
vidjon_messenger_api/resources/message.py
vidjon_messenger_api/resources/user.py
vidjon_messenger_api-2.0.dist-info/DESCRIPTION.rst
vidjon_messenger_api-2.0.dist-info/METADATA
vidjon_messenger_api-2.0.dist-info/RECORD
vidjon_messenger_api-2.0.dist-info/WHEEL
vidjon_messenger_api-2.0.dist-info/entry_points.txt
vidjon_messenger_api-2.0.dist-info/metadata.json
vidjon_messenger_api-2.0.dist-info/top_level.txt
